fastreer/cli.py
fastreer/inst/java/BioInfoJavaUtils-2.0.0.jar
fastreer/inst/java/jcommander-1.82.jar
fastreer/inst/java/trove4j-3.0.3.jar
fastreer-2.0.0.dist-info/licenses/LICENSE.md
fastreer-2.0.0.dist-info/METADATA
fastreer-2.0.0.dist-info/WHEEL
fastreer-2.0.0.dist-info/entry_points.txt
fastreer-2.0.0.dist-info/top_level.txt
fastreer-2.0.0.dist-info/RECORD
