Metadata-Version: 2.4
Name: fastreer
Version: 2.0.0
Summary: CLI toolkit for phylogenetic trees and distance matrices from VCF and FASTA
Home-page: https://github.com/gkanogiannis/fastreeR
Author: Anestis Gkanogiannis
Author-email: anestis@gkanogiannis.com
License-Expression: GPL-3.0-only
Project-URL: Source, https://github.com/gkanogiannis/fastreeR
Project-URL: Documentation, https://github.com/gkanogiannis/fastreeR#readme
Classifier: Programming Language :: Python :: 3
Classifier: Programming Language :: Java
Classifier: Operating System :: OS Independent
Requires-Python: >=3.7
License-File: LICENSE.md
Dynamic: license-file
Dynamic: license-expression
